{"max": 4060, "weeks": [{"date": "2015-12-28", "value": 23096}, {"date": "2016-01-04", "value": 17170}, {"date": "2016-01-11", "value": 16753}, {"date": "2016-01-18", "value": 16487}, {"date": "2016-01-25", "value": 17748}, {"date": "2016-02-01", "value": 17658}, {"date": "2016-02-08", "value": 17215}, {"date": "2016-02-15", "value": 17479}, {"date": "2016-02-22", "value": 16973}, {"date": "2016-02-29", "value": 18804}, {"date": "2016-03-07", "value": 17216}, {"date": "2016-03-14", "value": 17253}, {"date": "2016-03-21", "value": 18008}, {"date": "2016-03-28", "value": 17968}, {"date": "2016-04-04", "value": 17318}, {"date": "2016-04-11", "value": 16390}, {"date": "2016-04-18", "value": 16282}, {"date": "2016-04-25", "value": 17874}, {"date": "2016-05-02", "value": 17260}, {"date": "2016-05-09", "value": 16878}, {"date": "2016-05-16", "value": 18378}, {"date": "2016-05-23", "value": 17400}, {"date": "2016-05-30", "value": 16643}, {"date": "2016-06-06", "value": 15536}, {"date": "2016-06-13", "value": 16228}, {"date": "2016-06-20", "value": 14999}, {"date": "2016-06-27", "value": 15321}, {"date": "2016-07-04", "value": 15920}, {"date": "2016-07-11", "value": 15813}, {"date": "2016-07-18", "value": 14514}, {"date": "2016-07-25", "value": 16189}, {"date": "2016-08-01", "value": 16246}, {"date": "2016-08-08", "value": 14135}, {"date": "2016-08-15", "value": 15326}, {"date": "2016-08-22", "value": 16372}, {"date": "2016-08-29", "value": 16344}, {"date": "2016-09-05", "value": 16017}, {"date": "2016-09-12", "value": 15131}, {"date": "2016-09-19", "value": 15007}, {"date": "2016-09-26", "value": 15462}, {"date": "2016-10-03", "value": 14490}, {"date": "2016-10-10", "value": 13757}, {"date": "2016-10-17", "value": 14066}, {"date": "2016-10-24", "value": 15105}, {"date": "2016-10-31", "value": 13066}, {"date": "2016-11-07", "value": 15537}, {"date": "2016-11-14", "value": 15155}, {"date": "2016-11-21", "value": 16238}, {"date": "2016-11-28", "value": 15318}, {"date": "2016-12-05", "value": 15176}, {"date": "2016-12-12", "value": 15712}, {"date": "2016-12-19", "value": 16861}, {"date": "2016-12-26", "value": 17751}], "data": [{"date": "2015-12-28", "value": 3886}, {"date": "2015-12-29", "value": 3474}, {"date": "2015-12-30", "value": 2974}, {"date": "2015-12-31", "value": 3644}, {"date": "2016-01-01", "value": 3373}, {"date": "2016-01-02", "value": 2882}, {"date": "2016-01-03", "value": 2862}, {"date": "2016-01-04", "value": 2471}, {"date": "2016-01-05", "value": 2069}, {"date": "2016-01-06", "value": 2223}, {"date": "2016-01-07", "value": 2276}, {"date": "2016-01-08", "value": 2377}, {"date": "2016-01-09", "value": 2834}, {"date": "2016-01-10", "value": 2919}, {"date": "2016-01-11", "value": 2219}, {"date": "2016-01-12", "value": 1887}, {"date": "2016-01-13", "value": 2105}, {"date": "2016-01-14", "value": 2249}, {"date": "2016-01-15", "value": 2765}, {"date": "2016-01-16", "value": 2680}, {"date": "2016-01-17", "value": 2847}, {"date": "2016-01-18", "value": 2004}, {"date": "2016-01-19", "value": 1845}, {"date": "2016-01-20", "value": 2110}, {"date": "2016-01-21", "value": 2032}, {"date": "2016-01-22", "value": 2674}, {"date": "2016-01-23", "value": 3120}, {"date": "2016-01-24", "value": 2702}, {"date": "2016-01-25", "value": 2309}, {"date": "2016-01-26", "value": 2398}, {"date": "2016-01-27", "value": 2110}, {"date": "2016-01-28", "value": 2462}, {"date": "2016-01-29", "value": 2642}, {"date": "2016-01-30", "value": 2866}, {"date": "2016-01-31", "value": 2961}, {"date": "2016-02-01", "value": 1996}, {"date": "2016-02-02", "value": 1834}, {"date": "2016-02-03", "value": 2898}, {"date": "2016-02-04", "value": 2306}, {"date": "2016-02-05", "value": 2679}, {"date": "2016-02-06", "value": 3173}, {"date": "2016-02-07", "value": 2772}, {"date": "2016-02-08", "value": 1685}, {"date": "2016-02-09", "value": 2085}, {"date": "2016-02-10", "value": 2293}, {"date": "2016-02-11", "value": 2051}, {"date": "2016-02-12", "value": 2911}, {"date": "2016-02-13", "value": 3180}, {"date": "2016-02-14", "value": 3011}, {"date": "2016-02-15", "value": 2464}, {"date": "2016-02-16", "value": 2325}, {"date": "2016-02-17", "value": 2133}, {"date": "2016-02-18", "value": 2157}, {"date": "2016-02-19", "value": 2742}, {"date": "2016-02-20", "value": 3050}, {"date": "2016-02-21", "value": 2608}, {"date": "2016-02-22", "value": 2135}, {"date": "2016-02-23", "value": 2075}, {"date": "2016-02-24", "value": 2024}, {"date": "2016-02-25", "value": 2057}, {"date": "2016-02-26", "value": 2882}, {"date": "2016-02-27", "value": 2893}, {"date": "2016-02-28", "value": 2908}, {"date": "2016-02-29", "value": 2754}, {"date": "2016-03-01", "value": 2406}, {"date": "2016-03-02", "value": 2231}, {"date": "2016-03-03", "value": 2493}, {"date": "2016-03-04", "value": 2589}, {"date": "2016-03-05", "value": 3482}, {"date": "2016-03-06", "value": 2850}, {"date": "2016-03-07", "value": 1958}, {"date": "2016-03-08", "value": 2377}, {"date": "2016-03-09", "value": 2378}, {"date": "2016-03-10", "value": 2063}, {"date": "2016-03-11", "value": 2760}, {"date": "2016-03-12", "value": 2892}, {"date": "2016-03-13", "value": 2788}, {"date": "2016-03-14", "value": 2261}, {"date": "2016-03-15", "value": 2351}, {"date": "2016-03-16", "value": 1950}, {"date": "2016-03-17", "value": 2227}, {"date": "2016-03-18", "value": 2861}, {"date": "2016-03-19", "value": 2869}, {"date": "2016-03-20", "value": 2734}, {"date": "2016-03-21", "value": 2147}, {"date": "2016-03-22", "value": 2070}, {"date": "2016-03-23", "value": 2128}, {"date": "2016-03-24", "value": 2593}, {"date": "2016-03-25", "value": 3227}, {"date": "2016-03-26", "value": 2963}, {"date": "2016-03-27", "value": 2882}, {"date": "2016-03-28", "value": 2646}, {"date": "2016-03-29", "value": 2375}, {"date": "2016-03-30", "value": 2408}, {"date": "2016-03-31", "value": 2310}, {"date": "2016-04-01", "value": 2651}, {"date": "2016-04-02", "value": 2894}, {"date": "2016-04-03", "value": 2683}, {"date": "2016-04-04", "value": 2297}, {"date": "2016-04-05", "value": 2307}, {"date": "2016-04-06", "value": 2140}, {"date": "2016-04-07", "value": 2244}, {"date": "2016-04-08", "value": 2865}, {"date": "2016-04-09", "value": 2913}, {"date": "2016-04-10", "value": 2553}, {"date": "2016-04-11", "value": 2216}, {"date": "2016-04-12", "value": 2084}, {"date": "2016-04-13", "value": 2156}, {"date": "2016-04-14", "value": 2187}, {"date": "2016-04-15", "value": 2553}, {"date": "2016-04-16", "value": 2842}, {"date": "2016-04-17", "value": 2352}, {"date": "2016-04-18", "value": 2082}, {"date": "2016-04-19", "value": 1975}, {"date": "2016-04-20", "value": 2342}, {"date": "2016-04-21", "value": 1872}, {"date": "2016-04-22", "value": 2610}, {"date": "2016-04-23", "value": 2724}, {"date": "2016-04-24", "value": 2677}, {"date": "2016-04-25", "value": 1950}, {"date": "2016-04-26", "value": 2011}, {"date": "2016-04-27", "value": 2229}, {"date": "2016-04-28", "value": 2452}, {"date": "2016-04-29", "value": 2957}, {"date": "2016-04-30", "value": 3410}, {"date": "2016-05-01", "value": 2865}, {"date": "2016-05-02", "value": 2545}, {"date": "2016-05-03", "value": 2172}, {"date": "2016-05-04", "value": 2343}, {"date": "2016-05-05", "value": 2340}, {"date": "2016-05-06", "value": 2390}, {"date": "2016-05-07", "value": 2825}, {"date": "2016-05-08", "value": 2644}, {"date": "2016-05-09", "value": 2208}, {"date": "2016-05-10", "value": 2216}, {"date": "2016-05-11", "value": 2315}, {"date": "2016-05-12", "value": 2443}, {"date": "2016-05-13", "value": 2382}, {"date": "2016-05-14", "value": 2712}, {"date": "2016-05-15", "value": 2602}, {"date": "2016-05-16", "value": 2226}, {"date": "2016-05-17", "value": 2285}, {"date": "2016-05-18", "value": 2192}, {"date": "2016-05-19", "value": 2138}, {"date": "2016-05-20", "value": 4060}, {"date": "2016-05-21", "value": 2709}, {"date": "2016-05-22", "value": 2768}, {"date": "2016-05-23", "value": 2104}, {"date": "2016-05-24", "value": 2299}, {"date": "2016-05-25", "value": 2399}, {"date": "2016-05-26", "value": 2310}, {"date": "2016-05-27", "value": 2687}, {"date": "2016-05-28", "value": 2854}, {"date": "2016-05-29", "value": 2747}, {"date": "2016-05-30", "value": 2487}, {"date": "2016-05-31", "value": 2102}, {"date": "2016-06-01", "value": 2310}, {"date": "2016-06-02", "value": 2180}, {"date": "2016-06-03", "value": 2578}, {"date": "2016-06-04", "value": 2709}, {"date": "2016-06-05", "value": 2276}, {"date": "2016-06-06", "value": 2113}, {"date": "2016-06-07", "value": 1121}, {"date": "2016-06-08", "value": 2237}, {"date": "2016-06-09", "value": 2282}, {"date": "2016-06-10", "value": 2602}, {"date": "2016-06-11", "value": 2793}, {"date": "2016-06-12", "value": 2387}, {"date": "2016-06-13", "value": 1963}, {"date": "2016-06-14", "value": 2236}, {"date": "2016-06-15", "value": 2051}, {"date": "2016-06-16", "value": 2273}, {"date": "2016-06-17", "value": 2595}, {"date": "2016-06-18", "value": 2478}, {"date": "2016-06-19", "value": 2632}, {"date": "2016-06-20", "value": 1912}, {"date": "2016-06-21", "value": 2135}, {"date": "2016-06-22", "value": 2075}, {"date": "2016-06-23", "value": 1967}, {"date": "2016-06-24", "value": 2086}, {"date": "2016-06-25", "value": 2357}, {"date": "2016-06-26", "value": 2466}, {"date": "2016-06-27", "value": 1824}, {"date": "2016-06-28", "value": 1835}, {"date": "2016-06-29", "value": 2058}, {"date": "2016-06-30", "value": 2074}, {"date": "2016-07-01", "value": 2356}, {"date": "2016-07-02", "value": 2709}, {"date": "2016-07-03", "value": 2466}, {"date": "2016-07-04", "value": 2248}, {"date": "2016-07-05", "value": 1833}, {"date": "2016-07-06", "value": 1779}, {"date": "2016-07-07", "value": 2094}, {"date": "2016-07-08", "value": 2587}, {"date": "2016-07-09", "value": 2646}, {"date": "2016-07-10", "value": 2732}, {"date": "2016-07-11", "value": 2101}, {"date": "2016-07-12", "value": 1980}, {"date": "2016-07-13", "value": 2195}, {"date": "2016-07-14", "value": 2058}, {"date": "2016-07-15", "value": 2406}, {"date": "2016-07-16", "value": 2681}, {"date": "2016-07-17", "value": 2392}, {"date": "2016-07-18", "value": 1610}, {"date": "2016-07-19", "value": 1832}, {"date": "2016-07-20", "value": 1744}, {"date": "2016-07-21", "value": 1915}, {"date": "2016-07-22", "value": 2248}, {"date": "2016-07-23", "value": 2401}, {"date": "2016-07-24", "value": 2763}, {"date": "2016-07-25", "value": 2035}, {"date": "2016-07-26", "value": 2088}, {"date": "2016-07-27", "value": 2254}, {"date": "2016-07-28", "value": 2204}, {"date": "2016-07-29", "value": 2690}, {"date": "2016-07-30", "value": 2236}, {"date": "2016-07-31", "value": 2682}, {"date": "2016-08-01", "value": 2210}, {"date": "2016-08-02", "value": 2177}, {"date": "2016-08-03", "value": 2068}, {"date": "2016-08-04", "value": 2147}, {"date": "2016-08-05", "value": 2644}, {"date": "2016-08-06", "value": 2431}, {"date": "2016-08-07", "value": 2569}, {"date": "2016-08-08", "value": 2136}, {"date": "2016-08-09", "value": 2216}, {"date": "2016-08-10", "value": 1849}, {"date": "2016-08-11", "value": 1795}, {"date": "2016-08-12", "value": 1950}, {"date": "2016-08-13", "value": 2153}, {"date": "2016-08-14", "value": 2036}, {"date": "2016-08-15", "value": 1963}, {"date": "2016-08-16", "value": 1967}, {"date": "2016-08-17", "value": 2311}, {"date": "2016-08-18", "value": 1577}, {"date": "2016-08-19", "value": 2438}, {"date": "2016-08-20", "value": 2569}, {"date": "2016-08-21", "value": 2501}, {"date": "2016-08-22", "value": 2425}, {"date": "2016-08-23", "value": 2198}, {"date": "2016-08-24", "value": 2113}, {"date": "2016-08-25", "value": 2216}, {"date": "2016-08-26", "value": 2189}, {"date": "2016-08-27", "value": 2551}, {"date": "2016-08-28", "value": 2680}, {"date": "2016-08-29", "value": 2405}, {"date": "2016-08-30", "value": 2074}, {"date": "2016-08-31", "value": 2244}, {"date": "2016-09-01", "value": 2010}, {"date": "2016-09-02", "value": 2669}, {"date": "2016-09-03", "value": 2511}, {"date": "2016-09-04", "value": 2431}, {"date": "2016-09-05", "value": 2021}, {"date": "2016-09-06", "value": 2216}, {"date": "2016-09-07", "value": 1957}, {"date": "2016-09-08", "value": 2229}, {"date": "2016-09-09", "value": 2534}, {"date": "2016-09-10", "value": 2527}, {"date": "2016-09-11", "value": 2533}, {"date": "2016-09-12", "value": 2124}, {"date": "2016-09-13", "value": 1959}, {"date": "2016-09-14", "value": 1832}, {"date": "2016-09-15", "value": 1957}, {"date": "2016-09-16", "value": 2552}, {"date": "2016-09-17", "value": 2358}, {"date": "2016-09-18", "value": 2349}, {"date": "2016-09-19", "value": 1813}, {"date": "2016-09-20", "value": 1980}, {"date": "2016-09-21", "value": 2069}, {"date": "2016-09-22", "value": 1962}, {"date": "2016-09-23", "value": 2258}, {"date": "2016-09-24", "value": 2650}, {"date": "2016-09-25", "value": 2275}, {"date": "2016-09-26", "value": 2047}, {"date": "2016-09-27", "value": 1896}, {"date": "2016-09-28", "value": 2086}, {"date": "2016-09-29", "value": 1993}, {"date": "2016-09-30", "value": 2428}, {"date": "2016-10-01", "value": 2865}, {"date": "2016-10-02", "value": 2147}, {"date": "2016-10-03", "value": 1819}, {"date": "2016-10-04", "value": 1963}, {"date": "2016-10-05", "value": 2016}, {"date": "2016-10-06", "value": 1816}, {"date": "2016-10-07", "value": 2250}, {"date": "2016-10-08", "value": 2331}, {"date": "2016-10-09", "value": 2295}, {"date": "2016-10-10", "value": 1522}, {"date": "2016-10-11", "value": 1725}, {"date": "2016-10-12", "value": 1886}, {"date": "2016-10-13", "value": 1856}, {"date": "2016-10-14", "value": 2194}, {"date": "2016-10-15", "value": 2331}, {"date": "2016-10-16", "value": 2244}, {"date": "2016-10-17", "value": 1790}, {"date": "2016-10-18", "value": 1755}, {"date": "2016-10-19", "value": 1877}, {"date": "2016-10-20", "value": 1676}, {"date": "2016-10-21", "value": 2357}, {"date": "2016-10-22", "value": 2465}, {"date": "2016-10-23", "value": 2146}, {"date": "2016-10-24", "value": 1855}, {"date": "2016-10-25", "value": 1779}, {"date": "2016-10-26", "value": 2263}, {"date": "2016-10-27", "value": 2368}, {"date": "2016-10-28", "value": 2254}, {"date": "2016-10-29", "value": 2536}, {"date": "2016-10-30", "value": 2052}, {"date": "2016-10-31", "value": 1720}, {"date": "2016-11-01", "value": 1679}, {"date": "2016-11-02", "value": 1837}, {"date": "2016-11-03", "value": 1870}, {"date": "2016-11-04", "value": 1831}, {"date": "2016-11-05", "value": 2052}, {"date": "2016-11-06", "value": 2078}, {"date": "2016-11-07", "value": 1756}, {"date": "2016-11-08", "value": 1901}, {"date": "2016-11-09", "value": 2105}, {"date": "2016-11-10", "value": 2243}, {"date": "2016-11-11", "value": 2546}, {"date": "2016-11-12", "value": 2589}, {"date": "2016-11-13", "value": 2397}, {"date": "2016-11-14", "value": 1864}, {"date": "2016-11-15", "value": 2089}, {"date": "2016-11-16", "value": 1977}, {"date": "2016-11-17", "value": 1896}, {"date": "2016-11-18", "value": 2419}, {"date": "2016-11-19", "value": 2545}, {"date": "2016-11-20", "value": 2364}, {"date": "2016-11-21", "value": 1951}, {"date": "2016-11-22", "value": 2179}, {"date": "2016-11-23", "value": 2226}, {"date": "2016-11-24", "value": 2210}, {"date": "2016-11-25", "value": 2718}, {"date": "2016-11-26", "value": 2654}, {"date": "2016-11-27", "value": 2300}, {"date": "2016-11-28", "value": 2029}, {"date": "2016-11-29", "value": 1985}, {"date": "2016-11-30", "value": 2313}, {"date": "2016-12-01", "value": 1949}, {"date": "2016-12-02", "value": 2337}, {"date": "2016-12-03", "value": 2413}, {"date": "2016-12-04", "value": 2292}, {"date": "2016-12-05", "value": 2075}, {"date": "2016-12-06", "value": 2223}, {"date": "2016-12-07", "value": 2253}, {"date": "2016-12-08", "value": 1937}, {"date": "2016-12-09", "value": 2198}, {"date": "2016-12-10", "value": 2267}, {"date": "2016-12-11", "value": 2223}, {"date": "2016-12-12", "value": 1811}, {"date": "2016-12-13", "value": 2139}, {"date": "2016-12-14", "value": 2225}, {"date": "2016-12-15", "value": 2161}, {"date": "2016-12-16", "value": 2382}, {"date": "2016-12-17", "value": 2475}, {"date": "2016-12-18", "value": 2520}, {"date": "2016-12-19", "value": 1969}, {"date": "2016-12-20", "value": 1823}, {"date": "2016-12-21", "value": 2094}, {"date": "2016-12-22", "value": 2206}, {"date": "2016-12-23", "value": 2953}, {"date": "2016-12-24", "value": 2863}, {"date": "2016-12-25", "value": 2953}, {"date": "2016-12-26", "value": 2594}, {"date": "2016-12-27", "value": 2368}, {"date": "2016-12-28", "value": 2370}, {"date": "2016-12-29", "value": 2194}, {"date": "2016-12-30", "value": 2746}, {"date": "2016-12-31", "value": 2564}, {"date": "2017-01-01", "value": 2914}], "min": 1121}