{"max": 22816, "weeks": [{"date": "2015-12-28", "value": 79222}, {"date": "2016-01-04", "value": 54088}, {"date": "2016-01-11", "value": 53724}, {"date": "2016-01-18", "value": 53730}, {"date": "2016-01-25", "value": 61245}, {"date": "2016-02-01", "value": 59595}, {"date": "2016-02-08", "value": 62058}, {"date": "2016-02-15", "value": 58217}, {"date": "2016-02-22", "value": 64719}, {"date": "2016-02-29", "value": 72299}, {"date": "2016-03-07", "value": 60212}, {"date": "2016-03-14", "value": 61665}, {"date": "2016-03-21", "value": 66345}, {"date": "2016-03-28", "value": 66011}, {"date": "2016-04-04", "value": 61748}, {"date": "2016-04-11", "value": 65226}, {"date": "2016-04-18", "value": 61327}, {"date": "2016-04-25", "value": 63575}, {"date": "2016-05-02", "value": 65206}, {"date": "2016-05-09", "value": 62543}, {"date": "2016-05-16", "value": 67553}, {"date": "2016-05-23", "value": 57908}, {"date": "2016-05-30", "value": 62092}, {"date": "2016-06-06", "value": 51673}, {"date": "2016-06-13", "value": 54289}, {"date": "2016-06-20", "value": 56470}, {"date": "2016-06-27", "value": 60314}, {"date": "2016-07-04", "value": 51569}, {"date": "2016-07-11", "value": 47209}, {"date": "2016-07-18", "value": 50774}, {"date": "2016-07-25", "value": 49043}, {"date": "2016-08-01", "value": 52897}, {"date": "2016-08-08", "value": 50382}, {"date": "2016-08-15", "value": 54761}, {"date": "2016-08-22", "value": 53840}, {"date": "2016-08-29", "value": 57012}, {"date": "2016-09-05", "value": 54882}, {"date": "2016-09-12", "value": 53970}, {"date": "2016-09-19", "value": 55122}, {"date": "2016-09-26", "value": 55730}, {"date": "2016-10-03", "value": 55200}, {"date": "2016-10-10", "value": 53888}, {"date": "2016-10-17", "value": 54739}, {"date": "2016-10-24", "value": 55580}, {"date": "2016-10-31", "value": 56813}, {"date": "2016-11-07", "value": 58005}, {"date": "2016-11-14", "value": 55844}, {"date": "2016-11-21", "value": 74856}, {"date": "2016-11-28", "value": 67202}, {"date": "2016-12-05", "value": 75742}, {"date": "2016-12-12", "value": 75577}, {"date": "2016-12-19", "value": 101948}, {"date": "2016-12-26", "value": 110333}], "data": [{"date": "2015-12-28", "value": 12555}, {"date": "2015-12-29", "value": 12013}, {"date": "2015-12-30", "value": 10621}, {"date": "2015-12-31", "value": 14634}, {"date": "2016-01-01", "value": 10346}, {"date": "2016-01-02", "value": 10276}, {"date": "2016-01-03", "value": 8777}, {"date": "2016-01-04", "value": 7221}, {"date": "2016-01-05", "value": 6258}, {"date": "2016-01-06", "value": 7377}, {"date": "2016-01-07", "value": 8538}, {"date": "2016-01-08", "value": 7665}, {"date": "2016-01-09", "value": 8254}, {"date": "2016-01-10", "value": 8774}, {"date": "2016-01-11", "value": 6640}, {"date": "2016-01-12", "value": 5689}, {"date": "2016-01-13", "value": 6424}, {"date": "2016-01-14", "value": 7644}, {"date": "2016-01-15", "value": 9521}, {"date": "2016-01-16", "value": 9407}, {"date": "2016-01-17", "value": 8400}, {"date": "2016-01-18", "value": 6831}, {"date": "2016-01-19", "value": 7452}, {"date": "2016-01-20", "value": 6513}, {"date": "2016-01-21", "value": 7281}, {"date": "2016-01-22", "value": 8688}, {"date": "2016-01-23", "value": 9358}, {"date": "2016-01-24", "value": 7607}, {"date": "2016-01-25", "value": 7435}, {"date": "2016-01-26", "value": 7223}, {"date": "2016-01-27", "value": 7650}, {"date": "2016-01-28", "value": 8590}, {"date": "2016-01-29", "value": 11187}, {"date": "2016-01-30", "value": 10189}, {"date": "2016-01-31", "value": 8970}, {"date": "2016-02-01", "value": 8398}, {"date": "2016-02-02", "value": 7904}, {"date": "2016-02-03", "value": 8733}, {"date": "2016-02-04", "value": 8212}, {"date": "2016-02-05", "value": 8658}, {"date": "2016-02-06", "value": 9407}, {"date": "2016-02-07", "value": 8283}, {"date": "2016-02-08", "value": 7579}, {"date": "2016-02-09", "value": 7639}, {"date": "2016-02-10", "value": 8276}, {"date": "2016-02-11", "value": 8564}, {"date": "2016-02-12", "value": 10685}, {"date": "2016-02-13", "value": 9253}, {"date": "2016-02-14", "value": 10062}, {"date": "2016-02-15", "value": 7757}, {"date": "2016-02-16", "value": 6685}, {"date": "2016-02-17", "value": 7782}, {"date": "2016-02-18", "value": 8273}, {"date": "2016-02-19", "value": 9575}, {"date": "2016-02-20", "value": 9555}, {"date": "2016-02-21", "value": 8590}, {"date": "2016-02-22", "value": 8884}, {"date": "2016-02-23", "value": 7114}, {"date": "2016-02-24", "value": 8018}, {"date": "2016-02-25", "value": 8209}, {"date": "2016-02-26", "value": 11153}, {"date": "2016-02-27", "value": 10470}, {"date": "2016-02-28", "value": 10871}, {"date": "2016-02-29", "value": 9011}, {"date": "2016-03-01", "value": 8750}, {"date": "2016-03-02", "value": 9704}, {"date": "2016-03-03", "value": 12539}, {"date": "2016-03-04", "value": 10426}, {"date": "2016-03-05", "value": 11330}, {"date": "2016-03-06", "value": 10540}, {"date": "2016-03-07", "value": 6903}, {"date": "2016-03-08", "value": 7183}, {"date": "2016-03-09", "value": 7724}, {"date": "2016-03-10", "value": 8961}, {"date": "2016-03-11", "value": 10019}, {"date": "2016-03-12", "value": 10158}, {"date": "2016-03-13", "value": 9263}, {"date": "2016-03-14", "value": 8345}, {"date": "2016-03-15", "value": 8680}, {"date": "2016-03-16", "value": 7316}, {"date": "2016-03-17", "value": 8185}, {"date": "2016-03-18", "value": 9480}, {"date": "2016-03-19", "value": 9614}, {"date": "2016-03-20", "value": 10044}, {"date": "2016-03-21", "value": 8467}, {"date": "2016-03-22", "value": 6974}, {"date": "2016-03-23", "value": 7821}, {"date": "2016-03-24", "value": 11226}, {"date": "2016-03-25", "value": 10909}, {"date": "2016-03-26", "value": 9624}, {"date": "2016-03-27", "value": 11324}, {"date": "2016-03-28", "value": 8898}, {"date": "2016-03-29", "value": 8080}, {"date": "2016-03-30", "value": 8237}, {"date": "2016-03-31", "value": 9117}, {"date": "2016-04-01", "value": 10879}, {"date": "2016-04-02", "value": 10680}, {"date": "2016-04-03", "value": 10120}, {"date": "2016-04-04", "value": 7158}, {"date": "2016-04-05", "value": 7544}, {"date": "2016-04-06", "value": 7691}, {"date": "2016-04-07", "value": 8503}, {"date": "2016-04-08", "value": 10209}, {"date": "2016-04-09", "value": 11106}, {"date": "2016-04-10", "value": 9537}, {"date": "2016-04-11", "value": 8166}, {"date": "2016-04-12", "value": 8140}, {"date": "2016-04-13", "value": 8289}, {"date": "2016-04-14", "value": 8645}, {"date": "2016-04-15", "value": 10781}, {"date": "2016-04-16", "value": 10898}, {"date": "2016-04-17", "value": 10307}, {"date": "2016-04-18", "value": 9133}, {"date": "2016-04-19", "value": 8127}, {"date": "2016-04-20", "value": 7385}, {"date": "2016-04-21", "value": 8311}, {"date": "2016-04-22", "value": 9626}, {"date": "2016-04-23", "value": 9311}, {"date": "2016-04-24", "value": 9435}, {"date": "2016-04-25", "value": 7574}, {"date": "2016-04-26", "value": 7773}, {"date": "2016-04-27", "value": 7441}, {"date": "2016-04-28", "value": 8496}, {"date": "2016-04-29", "value": 11092}, {"date": "2016-04-30", "value": 10587}, {"date": "2016-05-01", "value": 10611}, {"date": "2016-05-02", "value": 8722}, {"date": "2016-05-03", "value": 7310}, {"date": "2016-05-04", "value": 8075}, {"date": "2016-05-05", "value": 8660}, {"date": "2016-05-06", "value": 10124}, {"date": "2016-05-07", "value": 11221}, {"date": "2016-05-08", "value": 11095}, {"date": "2016-05-09", "value": 7448}, {"date": "2016-05-10", "value": 8115}, {"date": "2016-05-11", "value": 8265}, {"date": "2016-05-12", "value": 9812}, {"date": "2016-05-13", "value": 9466}, {"date": "2016-05-14", "value": 10079}, {"date": "2016-05-15", "value": 9358}, {"date": "2016-05-16", "value": 7607}, {"date": "2016-05-17", "value": 8695}, {"date": "2016-05-18", "value": 8776}, {"date": "2016-05-19", "value": 9034}, {"date": "2016-05-20", "value": 12816}, {"date": "2016-05-21", "value": 10665}, {"date": "2016-05-22", "value": 9959}, {"date": "2016-05-23", "value": 7022}, {"date": "2016-05-24", "value": 7200}, {"date": "2016-05-25", "value": 7350}, {"date": "2016-05-26", "value": 8253}, {"date": "2016-05-27", "value": 8218}, {"date": "2016-05-28", "value": 9357}, {"date": "2016-05-29", "value": 10507}, {"date": "2016-05-30", "value": 9746}, {"date": "2016-05-31", "value": 8515}, {"date": "2016-06-01", "value": 7884}, {"date": "2016-06-02", "value": 8883}, {"date": "2016-06-03", "value": 9555}, {"date": "2016-06-04", "value": 9530}, {"date": "2016-06-05", "value": 7979}, {"date": "2016-06-06", "value": 7257}, {"date": "2016-06-07", "value": 3948}, {"date": "2016-06-08", "value": 7643}, {"date": "2016-06-09", "value": 7389}, {"date": "2016-06-10", "value": 8779}, {"date": "2016-06-11", "value": 8147}, {"date": "2016-06-12", "value": 8510}, {"date": "2016-06-13", "value": 8092}, {"date": "2016-06-14", "value": 5979}, {"date": "2016-06-15", "value": 6424}, {"date": "2016-06-16", "value": 7243}, {"date": "2016-06-17", "value": 9937}, {"date": "2016-06-18", "value": 8891}, {"date": "2016-06-19", "value": 7724}, {"date": "2016-06-20", "value": 7504}, {"date": "2016-06-21", "value": 7624}, {"date": "2016-06-22", "value": 7085}, {"date": "2016-06-23", "value": 8920}, {"date": "2016-06-24", "value": 9085}, {"date": "2016-06-25", "value": 7553}, {"date": "2016-06-26", "value": 8699}, {"date": "2016-06-27", "value": 8723}, {"date": "2016-06-28", "value": 7650}, {"date": "2016-06-29", "value": 7427}, {"date": "2016-06-30", "value": 9046}, {"date": "2016-07-01", "value": 9425}, {"date": "2016-07-02", "value": 9391}, {"date": "2016-07-03", "value": 8651}, {"date": "2016-07-04", "value": 7962}, {"date": "2016-07-05", "value": 6508}, {"date": "2016-07-06", "value": 6005}, {"date": "2016-07-07", "value": 7638}, {"date": "2016-07-08", "value": 8373}, {"date": "2016-07-09", "value": 7575}, {"date": "2016-07-10", "value": 7509}, {"date": "2016-07-11", "value": 6513}, {"date": "2016-07-12", "value": 5793}, {"date": "2016-07-13", "value": 6293}, {"date": "2016-07-14", "value": 6903}, {"date": "2016-07-15", "value": 7248}, {"date": "2016-07-16", "value": 7009}, {"date": "2016-07-17", "value": 7450}, {"date": "2016-07-18", "value": 6179}, {"date": "2016-07-19", "value": 5648}, {"date": "2016-07-20", "value": 6060}, {"date": "2016-07-21", "value": 7644}, {"date": "2016-07-22", "value": 8543}, {"date": "2016-07-23", "value": 9523}, {"date": "2016-07-24", "value": 7178}, {"date": "2016-07-25", "value": 6383}, {"date": "2016-07-26", "value": 6516}, {"date": "2016-07-27", "value": 6963}, {"date": "2016-07-28", "value": 6425}, {"date": "2016-07-29", "value": 8229}, {"date": "2016-07-30", "value": 7053}, {"date": "2016-07-31", "value": 7473}, {"date": "2016-08-01", "value": 6419}, {"date": "2016-08-02", "value": 5956}, {"date": "2016-08-03", "value": 6800}, {"date": "2016-08-04", "value": 7756}, {"date": "2016-08-05", "value": 9632}, {"date": "2016-08-06", "value": 8047}, {"date": "2016-08-07", "value": 8287}, {"date": "2016-08-08", "value": 6822}, {"date": "2016-08-09", "value": 6134}, {"date": "2016-08-10", "value": 7110}, {"date": "2016-08-11", "value": 7134}, {"date": "2016-08-12", "value": 9111}, {"date": "2016-08-13", "value": 6820}, {"date": "2016-08-14", "value": 7251}, {"date": "2016-08-15", "value": 6141}, {"date": "2016-08-16", "value": 6670}, {"date": "2016-08-17", "value": 7687}, {"date": "2016-08-18", "value": 5993}, {"date": "2016-08-19", "value": 9168}, {"date": "2016-08-20", "value": 9443}, {"date": "2016-08-21", "value": 9658}, {"date": "2016-08-22", "value": 6729}, {"date": "2016-08-23", "value": 7359}, {"date": "2016-08-24", "value": 7673}, {"date": "2016-08-25", "value": 7246}, {"date": "2016-08-26", "value": 8613}, {"date": "2016-08-27", "value": 8594}, {"date": "2016-08-28", "value": 7627}, {"date": "2016-08-29", "value": 6441}, {"date": "2016-08-30", "value": 8522}, {"date": "2016-08-31", "value": 7797}, {"date": "2016-09-01", "value": 8251}, {"date": "2016-09-02", "value": 9283}, {"date": "2016-09-03", "value": 8289}, {"date": "2016-09-04", "value": 8429}, {"date": "2016-09-05", "value": 7201}, {"date": "2016-09-06", "value": 6621}, {"date": "2016-09-07", "value": 7629}, {"date": "2016-09-08", "value": 9485}, {"date": "2016-09-09", "value": 7475}, {"date": "2016-09-10", "value": 8642}, {"date": "2016-09-11", "value": 7829}, {"date": "2016-09-12", "value": 6319}, {"date": "2016-09-13", "value": 7555}, {"date": "2016-09-14", "value": 6619}, {"date": "2016-09-15", "value": 8564}, {"date": "2016-09-16", "value": 8437}, {"date": "2016-09-17", "value": 8338}, {"date": "2016-09-18", "value": 8138}, {"date": "2016-09-19", "value": 6962}, {"date": "2016-09-20", "value": 6960}, {"date": "2016-09-21", "value": 6569}, {"date": "2016-09-22", "value": 7685}, {"date": "2016-09-23", "value": 8888}, {"date": "2016-09-24", "value": 9840}, {"date": "2016-09-25", "value": 8218}, {"date": "2016-09-26", "value": 6628}, {"date": "2016-09-27", "value": 6624}, {"date": "2016-09-28", "value": 6733}, {"date": "2016-09-29", "value": 8383}, {"date": "2016-09-30", "value": 8602}, {"date": "2016-10-01", "value": 10301}, {"date": "2016-10-02", "value": 8459}, {"date": "2016-10-03", "value": 7982}, {"date": "2016-10-04", "value": 7730}, {"date": "2016-10-05", "value": 7457}, {"date": "2016-10-06", "value": 6730}, {"date": "2016-10-07", "value": 7697}, {"date": "2016-10-08", "value": 8636}, {"date": "2016-10-09", "value": 8967}, {"date": "2016-10-10", "value": 6809}, {"date": "2016-10-11", "value": 6533}, {"date": "2016-10-12", "value": 7286}, {"date": "2016-10-13", "value": 7593}, {"date": "2016-10-14", "value": 8881}, {"date": "2016-10-15", "value": 8385}, {"date": "2016-10-16", "value": 8401}, {"date": "2016-10-17", "value": 7736}, {"date": "2016-10-18", "value": 7179}, {"date": "2016-10-19", "value": 6165}, {"date": "2016-10-20", "value": 8084}, {"date": "2016-10-21", "value": 9341}, {"date": "2016-10-22", "value": 8016}, {"date": "2016-10-23", "value": 8218}, {"date": "2016-10-24", "value": 7159}, {"date": "2016-10-25", "value": 7066}, {"date": "2016-10-26", "value": 6952}, {"date": "2016-10-27", "value": 7704}, {"date": "2016-10-28", "value": 7809}, {"date": "2016-10-29", "value": 9408}, {"date": "2016-10-30", "value": 9482}, {"date": "2016-10-31", "value": 7010}, {"date": "2016-11-01", "value": 7364}, {"date": "2016-11-02", "value": 7789}, {"date": "2016-11-03", "value": 8050}, {"date": "2016-11-04", "value": 8965}, {"date": "2016-11-05", "value": 9148}, {"date": "2016-11-06", "value": 8488}, {"date": "2016-11-07", "value": 6836}, {"date": "2016-11-08", "value": 7986}, {"date": "2016-11-09", "value": 8131}, {"date": "2016-11-10", "value": 9001}, {"date": "2016-11-11", "value": 9627}, {"date": "2016-11-12", "value": 8821}, {"date": "2016-11-13", "value": 7603}, {"date": "2016-11-14", "value": 5687}, {"date": "2016-11-15", "value": 7096}, {"date": "2016-11-16", "value": 7484}, {"date": "2016-11-17", "value": 7964}, {"date": "2016-11-18", "value": 9135}, {"date": "2016-11-19", "value": 9435}, {"date": "2016-11-20", "value": 9043}, {"date": "2016-11-21", "value": 7502}, {"date": "2016-11-22", "value": 7753}, {"date": "2016-11-23", "value": 8952}, {"date": "2016-11-24", "value": 12372}, {"date": "2016-11-25", "value": 14656}, {"date": "2016-11-26", "value": 12217}, {"date": "2016-11-27", "value": 11403}, {"date": "2016-11-28", "value": 8884}, {"date": "2016-11-29", "value": 8437}, {"date": "2016-11-30", "value": 9320}, {"date": "2016-12-01", "value": 9787}, {"date": "2016-12-02", "value": 10319}, {"date": "2016-12-03", "value": 10804}, {"date": "2016-12-04", "value": 9652}, {"date": "2016-12-05", "value": 8557}, {"date": "2016-12-06", "value": 9588}, {"date": "2016-12-07", "value": 9498}, {"date": "2016-12-08", "value": 10282}, {"date": "2016-12-09", "value": 12962}, {"date": "2016-12-10", "value": 13120}, {"date": "2016-12-11", "value": 11734}, {"date": "2016-12-12", "value": 8134}, {"date": "2016-12-13", "value": 9345}, {"date": "2016-12-14", "value": 9994}, {"date": "2016-12-15", "value": 11224}, {"date": "2016-12-16", "value": 13028}, {"date": "2016-12-17", "value": 12509}, {"date": "2016-12-18", "value": 11343}, {"date": "2016-12-19", "value": 9274}, {"date": "2016-12-20", "value": 10705}, {"date": "2016-12-21", "value": 11965}, {"date": "2016-12-22", "value": 13820}, {"date": "2016-12-23", "value": 16968}, {"date": "2016-12-24", "value": 16401}, {"date": "2016-12-25", "value": 22816}, {"date": "2016-12-26", "value": 17171}, {"date": "2016-12-27", "value": 13185}, {"date": "2016-12-28", "value": 14524}, {"date": "2016-12-29", "value": 14031}, {"date": "2016-12-30", "value": 17077}, {"date": "2016-12-31", "value": 17091}, {"date": "2017-01-01", "value": 17255}], "min": 3948}