{"max": 2024, "weeks": [{"date": "2015-12-28", "value": 6914}, {"date": "2016-01-04", "value": 6737}, {"date": "2016-01-11", "value": 6244}, {"date": "2016-01-18", "value": 6462}, {"date": "2016-01-25", "value": 7124}, {"date": "2016-02-01", "value": 7127}, {"date": "2016-02-08", "value": 6362}, {"date": "2016-02-15", "value": 6613}, {"date": "2016-02-22", "value": 7365}, {"date": "2016-02-29", "value": 7947}, {"date": "2016-03-07", "value": 6108}, {"date": "2016-03-14", "value": 6348}, {"date": "2016-03-21", "value": 7688}, {"date": "2016-03-28", "value": 7939}, {"date": "2016-04-04", "value": 7241}, {"date": "2016-04-11", "value": 7163}, {"date": "2016-04-18", "value": 7198}, {"date": "2016-04-25", "value": 7394}, {"date": "2016-05-02", "value": 6911}, {"date": "2016-05-09", "value": 7157}, {"date": "2016-05-16", "value": 8172}, {"date": "2016-05-23", "value": 6735}, {"date": "2016-05-30", "value": 7224}, {"date": "2016-06-06", "value": 6532}, {"date": "2016-06-13", "value": 6374}, {"date": "2016-06-20", "value": 6452}, {"date": "2016-06-27", "value": 6646}, {"date": "2016-07-04", "value": 6335}, {"date": "2016-07-11", "value": 6399}, {"date": "2016-07-18", "value": 6330}, {"date": "2016-07-25", "value": 6986}, {"date": "2016-08-01", "value": 6717}, {"date": "2016-08-08", "value": 6372}, {"date": "2016-08-15", "value": 7276}, {"date": "2016-08-22", "value": 6849}, {"date": "2016-08-29", "value": 7381}, {"date": "2016-09-05", "value": 6994}, {"date": "2016-09-12", "value": 6398}, {"date": "2016-09-19", "value": 6261}, {"date": "2016-09-26", "value": 6494}, {"date": "2016-10-03", "value": 6096}, {"date": "2016-10-10", "value": 6317}, {"date": "2016-10-17", "value": 6638}, {"date": "2016-10-24", "value": 6919}, {"date": "2016-10-31", "value": 6648}, {"date": "2016-11-07", "value": 7005}, {"date": "2016-11-14", "value": 6578}, {"date": "2016-11-21", "value": 7894}, {"date": "2016-11-28", "value": 7548}, {"date": "2016-12-05", "value": 7777}, {"date": "2016-12-12", "value": 7039}, {"date": "2016-12-19", "value": 8938}, {"date": "2016-12-26", "value": 9180}], "data": [{"date": "2015-12-28", "value": 835}, {"date": "2015-12-29", "value": 909}, {"date": "2015-12-30", "value": 1005}, {"date": "2015-12-31", "value": 1004}, {"date": "2016-01-01", "value": 1029}, {"date": "2016-01-02", "value": 1049}, {"date": "2016-01-03", "value": 1084}, {"date": "2016-01-04", "value": 956}, {"date": "2016-01-05", "value": 674}, {"date": "2016-01-06", "value": 911}, {"date": "2016-01-07", "value": 1032}, {"date": "2016-01-08", "value": 943}, {"date": "2016-01-09", "value": 1055}, {"date": "2016-01-10", "value": 1165}, {"date": "2016-01-11", "value": 930}, {"date": "2016-01-12", "value": 733}, {"date": "2016-01-13", "value": 830}, {"date": "2016-01-14", "value": 690}, {"date": "2016-01-15", "value": 1037}, {"date": "2016-01-16", "value": 994}, {"date": "2016-01-17", "value": 1031}, {"date": "2016-01-18", "value": 819}, {"date": "2016-01-19", "value": 930}, {"date": "2016-01-20", "value": 740}, {"date": "2016-01-21", "value": 970}, {"date": "2016-01-22", "value": 882}, {"date": "2016-01-23", "value": 1072}, {"date": "2016-01-24", "value": 1050}, {"date": "2016-01-25", "value": 948}, {"date": "2016-01-26", "value": 990}, {"date": "2016-01-27", "value": 815}, {"date": "2016-01-28", "value": 981}, {"date": "2016-01-29", "value": 1194}, {"date": "2016-01-30", "value": 1052}, {"date": "2016-01-31", "value": 1145}, {"date": "2016-02-01", "value": 904}, {"date": "2016-02-02", "value": 1096}, {"date": "2016-02-03", "value": 937}, {"date": "2016-02-04", "value": 1043}, {"date": "2016-02-05", "value": 868}, {"date": "2016-02-06", "value": 1092}, {"date": "2016-02-07", "value": 1186}, {"date": "2016-02-08", "value": 789}, {"date": "2016-02-09", "value": 896}, {"date": "2016-02-10", "value": 792}, {"date": "2016-02-11", "value": 944}, {"date": "2016-02-12", "value": 988}, {"date": "2016-02-13", "value": 1011}, {"date": "2016-02-14", "value": 942}, {"date": "2016-02-15", "value": 884}, {"date": "2016-02-16", "value": 941}, {"date": "2016-02-17", "value": 795}, {"date": "2016-02-18", "value": 897}, {"date": "2016-02-19", "value": 966}, {"date": "2016-02-20", "value": 1010}, {"date": "2016-02-21", "value": 1120}, {"date": "2016-02-22", "value": 833}, {"date": "2016-02-23", "value": 854}, {"date": "2016-02-24", "value": 993}, {"date": "2016-02-25", "value": 890}, {"date": "2016-02-26", "value": 1071}, {"date": "2016-02-27", "value": 1294}, {"date": "2016-02-28", "value": 1429}, {"date": "2016-02-29", "value": 1147}, {"date": "2016-03-01", "value": 1168}, {"date": "2016-03-02", "value": 1190}, {"date": "2016-03-03", "value": 1195}, {"date": "2016-03-04", "value": 1038}, {"date": "2016-03-05", "value": 1059}, {"date": "2016-03-06", "value": 1148}, {"date": "2016-03-07", "value": 809}, {"date": "2016-03-08", "value": 845}, {"date": "2016-03-09", "value": 756}, {"date": "2016-03-10", "value": 923}, {"date": "2016-03-11", "value": 924}, {"date": "2016-03-12", "value": 965}, {"date": "2016-03-13", "value": 886}, {"date": "2016-03-14", "value": 924}, {"date": "2016-03-15", "value": 842}, {"date": "2016-03-16", "value": 697}, {"date": "2016-03-17", "value": 858}, {"date": "2016-03-18", "value": 1024}, {"date": "2016-03-19", "value": 1086}, {"date": "2016-03-20", "value": 916}, {"date": "2016-03-21", "value": 971}, {"date": "2016-03-22", "value": 786}, {"date": "2016-03-23", "value": 1002}, {"date": "2016-03-24", "value": 1135}, {"date": "2016-03-25", "value": 1274}, {"date": "2016-03-26", "value": 1300}, {"date": "2016-03-27", "value": 1220}, {"date": "2016-03-28", "value": 1141}, {"date": "2016-03-29", "value": 1080}, {"date": "2016-03-30", "value": 1009}, {"date": "2016-03-31", "value": 1041}, {"date": "2016-04-01", "value": 1288}, {"date": "2016-04-02", "value": 1132}, {"date": "2016-04-03", "value": 1248}, {"date": "2016-04-04", "value": 904}, {"date": "2016-04-05", "value": 1017}, {"date": "2016-04-06", "value": 1161}, {"date": "2016-04-07", "value": 1018}, {"date": "2016-04-08", "value": 1048}, {"date": "2016-04-09", "value": 1085}, {"date": "2016-04-10", "value": 1010}, {"date": "2016-04-11", "value": 980}, {"date": "2016-04-12", "value": 813}, {"date": "2016-04-13", "value": 862}, {"date": "2016-04-14", "value": 1105}, {"date": "2016-04-15", "value": 1138}, {"date": "2016-04-16", "value": 1127}, {"date": "2016-04-17", "value": 1138}, {"date": "2016-04-18", "value": 1041}, {"date": "2016-04-19", "value": 887}, {"date": "2016-04-20", "value": 902}, {"date": "2016-04-21", "value": 1032}, {"date": "2016-04-22", "value": 980}, {"date": "2016-04-23", "value": 1236}, {"date": "2016-04-24", "value": 1120}, {"date": "2016-04-25", "value": 1085}, {"date": "2016-04-26", "value": 964}, {"date": "2016-04-27", "value": 1132}, {"date": "2016-04-28", "value": 1034}, {"date": "2016-04-29", "value": 1149}, {"date": "2016-04-30", "value": 1028}, {"date": "2016-05-01", "value": 1002}, {"date": "2016-05-02", "value": 1068}, {"date": "2016-05-03", "value": 751}, {"date": "2016-05-04", "value": 993}, {"date": "2016-05-05", "value": 911}, {"date": "2016-05-06", "value": 1046}, {"date": "2016-05-07", "value": 1092}, {"date": "2016-05-08", "value": 1052}, {"date": "2016-05-09", "value": 927}, {"date": "2016-05-10", "value": 1078}, {"date": "2016-05-11", "value": 973}, {"date": "2016-05-12", "value": 1033}, {"date": "2016-05-13", "value": 1077}, {"date": "2016-05-14", "value": 1105}, {"date": "2016-05-15", "value": 964}, {"date": "2016-05-16", "value": 791}, {"date": "2016-05-17", "value": 1016}, {"date": "2016-05-18", "value": 1018}, {"date": "2016-05-19", "value": 1081}, {"date": "2016-05-20", "value": 2024}, {"date": "2016-05-21", "value": 1123}, {"date": "2016-05-22", "value": 1119}, {"date": "2016-05-23", "value": 845}, {"date": "2016-05-24", "value": 824}, {"date": "2016-05-25", "value": 895}, {"date": "2016-05-26", "value": 952}, {"date": "2016-05-27", "value": 1052}, {"date": "2016-05-28", "value": 1075}, {"date": "2016-05-29", "value": 1092}, {"date": "2016-05-30", "value": 937}, {"date": "2016-05-31", "value": 1177}, {"date": "2016-06-01", "value": 910}, {"date": "2016-06-02", "value": 1036}, {"date": "2016-06-03", "value": 1125}, {"date": "2016-06-04", "value": 1081}, {"date": "2016-06-05", "value": 958}, {"date": "2016-06-06", "value": 858}, {"date": "2016-06-07", "value": 283}, {"date": "2016-06-08", "value": 1269}, {"date": "2016-06-09", "value": 912}, {"date": "2016-06-10", "value": 1019}, {"date": "2016-06-11", "value": 1138}, {"date": "2016-06-12", "value": 1053}, {"date": "2016-06-13", "value": 922}, {"date": "2016-06-14", "value": 696}, {"date": "2016-06-15", "value": 879}, {"date": "2016-06-16", "value": 813}, {"date": "2016-06-17", "value": 1101}, {"date": "2016-06-18", "value": 1132}, {"date": "2016-06-19", "value": 831}, {"date": "2016-06-20", "value": 845}, {"date": "2016-06-21", "value": 866}, {"date": "2016-06-22", "value": 895}, {"date": "2016-06-23", "value": 1054}, {"date": "2016-06-24", "value": 887}, {"date": "2016-06-25", "value": 966}, {"date": "2016-06-26", "value": 938}, {"date": "2016-06-27", "value": 878}, {"date": "2016-06-28", "value": 849}, {"date": "2016-06-29", "value": 1019}, {"date": "2016-06-30", "value": 1051}, {"date": "2016-07-01", "value": 962}, {"date": "2016-07-02", "value": 1031}, {"date": "2016-07-03", "value": 856}, {"date": "2016-07-04", "value": 666}, {"date": "2016-07-05", "value": 798}, {"date": "2016-07-06", "value": 926}, {"date": "2016-07-07", "value": 947}, {"date": "2016-07-08", "value": 951}, {"date": "2016-07-09", "value": 1044}, {"date": "2016-07-10", "value": 1004}, {"date": "2016-07-11", "value": 822}, {"date": "2016-07-12", "value": 940}, {"date": "2016-07-13", "value": 833}, {"date": "2016-07-14", "value": 926}, {"date": "2016-07-15", "value": 936}, {"date": "2016-07-16", "value": 961}, {"date": "2016-07-17", "value": 981}, {"date": "2016-07-18", "value": 774}, {"date": "2016-07-19", "value": 815}, {"date": "2016-07-20", "value": 849}, {"date": "2016-07-21", "value": 947}, {"date": "2016-07-22", "value": 886}, {"date": "2016-07-23", "value": 1115}, {"date": "2016-07-24", "value": 944}, {"date": "2016-07-25", "value": 842}, {"date": "2016-07-26", "value": 1023}, {"date": "2016-07-27", "value": 989}, {"date": "2016-07-28", "value": 1065}, {"date": "2016-07-29", "value": 1034}, {"date": "2016-07-30", "value": 973}, {"date": "2016-07-31", "value": 1060}, {"date": "2016-08-01", "value": 903}, {"date": "2016-08-02", "value": 783}, {"date": "2016-08-03", "value": 838}, {"date": "2016-08-04", "value": 1042}, {"date": "2016-08-05", "value": 1115}, {"date": "2016-08-06", "value": 1016}, {"date": "2016-08-07", "value": 1020}, {"date": "2016-08-08", "value": 1081}, {"date": "2016-08-09", "value": 797}, {"date": "2016-08-10", "value": 786}, {"date": "2016-08-11", "value": 1026}, {"date": "2016-08-12", "value": 967}, {"date": "2016-08-13", "value": 903}, {"date": "2016-08-14", "value": 811}, {"date": "2016-08-15", "value": 832}, {"date": "2016-08-16", "value": 940}, {"date": "2016-08-17", "value": 953}, {"date": "2016-08-18", "value": 983}, {"date": "2016-08-19", "value": 1106}, {"date": "2016-08-20", "value": 1258}, {"date": "2016-08-21", "value": 1203}, {"date": "2016-08-22", "value": 874}, {"date": "2016-08-23", "value": 889}, {"date": "2016-08-24", "value": 926}, {"date": "2016-08-25", "value": 873}, {"date": "2016-08-26", "value": 1108}, {"date": "2016-08-27", "value": 1171}, {"date": "2016-08-28", "value": 1007}, {"date": "2016-08-29", "value": 985}, {"date": "2016-08-30", "value": 937}, {"date": "2016-08-31", "value": 1039}, {"date": "2016-09-01", "value": 1010}, {"date": "2016-09-02", "value": 1100}, {"date": "2016-09-03", "value": 1266}, {"date": "2016-09-04", "value": 1044}, {"date": "2016-09-05", "value": 961}, {"date": "2016-09-06", "value": 935}, {"date": "2016-09-07", "value": 926}, {"date": "2016-09-08", "value": 1153}, {"date": "2016-09-09", "value": 865}, {"date": "2016-09-10", "value": 1179}, {"date": "2016-09-11", "value": 975}, {"date": "2016-09-12", "value": 747}, {"date": "2016-09-13", "value": 932}, {"date": "2016-09-14", "value": 766}, {"date": "2016-09-15", "value": 994}, {"date": "2016-09-16", "value": 1028}, {"date": "2016-09-17", "value": 990}, {"date": "2016-09-18", "value": 941}, {"date": "2016-09-19", "value": 829}, {"date": "2016-09-20", "value": 888}, {"date": "2016-09-21", "value": 787}, {"date": "2016-09-22", "value": 825}, {"date": "2016-09-23", "value": 963}, {"date": "2016-09-24", "value": 1044}, {"date": "2016-09-25", "value": 926}, {"date": "2016-09-26", "value": 854}, {"date": "2016-09-27", "value": 826}, {"date": "2016-09-28", "value": 923}, {"date": "2016-09-29", "value": 796}, {"date": "2016-09-30", "value": 1043}, {"date": "2016-10-01", "value": 1148}, {"date": "2016-10-02", "value": 905}, {"date": "2016-10-03", "value": 806}, {"date": "2016-10-04", "value": 805}, {"date": "2016-10-05", "value": 776}, {"date": "2016-10-06", "value": 770}, {"date": "2016-10-07", "value": 885}, {"date": "2016-10-08", "value": 958}, {"date": "2016-10-09", "value": 1095}, {"date": "2016-10-10", "value": 766}, {"date": "2016-10-11", "value": 874}, {"date": "2016-10-12", "value": 814}, {"date": "2016-10-13", "value": 840}, {"date": "2016-10-14", "value": 957}, {"date": "2016-10-15", "value": 1066}, {"date": "2016-10-16", "value": 1001}, {"date": "2016-10-17", "value": 932}, {"date": "2016-10-18", "value": 951}, {"date": "2016-10-19", "value": 860}, {"date": "2016-10-20", "value": 892}, {"date": "2016-10-21", "value": 875}, {"date": "2016-10-22", "value": 950}, {"date": "2016-10-23", "value": 1179}, {"date": "2016-10-24", "value": 982}, {"date": "2016-10-25", "value": 879}, {"date": "2016-10-26", "value": 901}, {"date": "2016-10-27", "value": 1004}, {"date": "2016-10-28", "value": 880}, {"date": "2016-10-29", "value": 1064}, {"date": "2016-10-30", "value": 1209}, {"date": "2016-10-31", "value": 988}, {"date": "2016-11-01", "value": 841}, {"date": "2016-11-02", "value": 994}, {"date": "2016-11-03", "value": 932}, {"date": "2016-11-04", "value": 952}, {"date": "2016-11-05", "value": 977}, {"date": "2016-11-06", "value": 964}, {"date": "2016-11-07", "value": 792}, {"date": "2016-11-08", "value": 1011}, {"date": "2016-11-09", "value": 989}, {"date": "2016-11-10", "value": 1069}, {"date": "2016-11-11", "value": 1036}, {"date": "2016-11-12", "value": 1136}, {"date": "2016-11-13", "value": 972}, {"date": "2016-11-14", "value": 776}, {"date": "2016-11-15", "value": 1000}, {"date": "2016-11-16", "value": 957}, {"date": "2016-11-17", "value": 947}, {"date": "2016-11-18", "value": 928}, {"date": "2016-11-19", "value": 1006}, {"date": "2016-11-20", "value": 965}, {"date": "2016-11-21", "value": 917}, {"date": "2016-11-22", "value": 903}, {"date": "2016-11-23", "value": 944}, {"date": "2016-11-24", "value": 1193}, {"date": "2016-11-25", "value": 1513}, {"date": "2016-11-26", "value": 1299}, {"date": "2016-11-27", "value": 1125}, {"date": "2016-11-28", "value": 1038}, {"date": "2016-11-29", "value": 1017}, {"date": "2016-11-30", "value": 1071}, {"date": "2016-12-01", "value": 1045}, {"date": "2016-12-02", "value": 1071}, {"date": "2016-12-03", "value": 1213}, {"date": "2016-12-04", "value": 1094}, {"date": "2016-12-05", "value": 963}, {"date": "2016-12-06", "value": 1065}, {"date": "2016-12-07", "value": 1037}, {"date": "2016-12-08", "value": 1191}, {"date": "2016-12-09", "value": 1103}, {"date": "2016-12-10", "value": 1204}, {"date": "2016-12-11", "value": 1214}, {"date": "2016-12-12", "value": 703}, {"date": "2016-12-13", "value": 973}, {"date": "2016-12-14", "value": 1025}, {"date": "2016-12-15", "value": 979}, {"date": "2016-12-16", "value": 1116}, {"date": "2016-12-17", "value": 1210}, {"date": "2016-12-18", "value": 1033}, {"date": "2016-12-19", "value": 1035}, {"date": "2016-12-20", "value": 1032}, {"date": "2016-12-21", "value": 1108}, {"date": "2016-12-22", "value": 1324}, {"date": "2016-12-23", "value": 1656}, {"date": "2016-12-24", "value": 1428}, {"date": "2016-12-25", "value": 1355}, {"date": "2016-12-26", "value": 1052}, {"date": "2016-12-27", "value": 1236}, {"date": "2016-12-28", "value": 1475}, {"date": "2016-12-29", "value": 1240}, {"date": "2016-12-30", "value": 1430}, {"date": "2016-12-31", "value": 1283}, {"date": "2017-01-01", "value": 1464}], "min": 283}